{"errors":[],"warnings":[],"namedChunkGroups":{"polyfill":{"chunks":[0,4],"assets":["webpack-runtime-6212285c208e85927d69.js","webpack-runtime-6212285c208e85927d69.js.map","polyfill-3f5d4f7e412d8cec1bfb.js","polyfill-3f5d4f7e412d8cec1bfb.js.map"],"children":{},"childAssets":{}},"app":{"chunks":[0,3,1],"assets":["webpack-runtime-6212285c208e85927d69.js","webpack-runtime-6212285c208e85927d69.js.map","framework-05e34eb4b3d8578f0642.js","framework-05e34eb4b3d8578f0642.js.map","app-1c3654e8a6b599bcda13.js","app-1c3654e8a6b599bcda13.js.map"],"children":{},"childAssets":{}},"component---src-pages-index-js":{"chunks":[5,2],"assets":["styles.5a6c6411731d04e25771.css","styles-29163f9dced6fe4a408a.js","styles-29163f9dced6fe4a408a.js.map","component---src-pages-index-js-b85436b16a18b4bbccee.js","component---src-pages-index-js-b85436b16a18b4bbccee.js.map"],"children":{},"childAssets":{}}},"assetsByChunkName":{"polyfill":["webpack-runtime-6212285c208e85927d69.js","polyfill-3f5d4f7e412d8cec1bfb.js"],"app":["webpack-runtime-6212285c208e85927d69.js","framework-05e34eb4b3d8578f0642.js","app-1c3654e8a6b599bcda13.js"],"component---src-pages-index-js":["styles.5a6c6411731d04e25771.css","styles-29163f9dced6fe4a408a.js","component---src-pages-index-js-b85436b16a18b4bbccee.js"]}}